bamos_opt/__init__.py
bamos_opt/pgd.py
bamos_opt/spg.py
bamos_opt-0.0.1.dist-info/DESCRIPTION.rst
bamos_opt-0.0.1.dist-info/METADATA
bamos_opt-0.0.1.dist-info/RECORD
bamos_opt-0.0.1.dist-info/WHEEL
bamos_opt-0.0.1.dist-info/metadata.json
bamos_opt-0.0.1.dist-info/top_level.txt
